<?xml version="1.0" encoding="utf-8" ?>
<Orders>
  <Order OrderID="10248">
    <CategoryID>2</CategoryID>
    <SubCategoryName>Sub Category 1</SubCategoryName>
    <SubCategoryTotal>Categories: 6 / Products: 25</SubCategoryTotal>
    <SubCategoryOperation></SubCategoryOperation>
    <SubCategoryLastUpdate>Feb 10 2016 - 16:35</SubCategoryLastUpdate>
	<SubCategoryStatus>Active</SubCategoryStatus>
    <SubCategoryAction></SubCategoryAction>
  </Order>
  <Order OrderID="10249">
    <CategoryID>1</CategoryID>
    <SubCategoryName>Sub Category 1</SubCategoryName>
    <SubCategoryTotal>Categories: 9 / Products: 15</SubCategoryTotal>
    <SubCategoryOperation></SubCategoryOperation>
    <SubCategoryLastUpdate>Feb 09 2016 - 13:15</SubCategoryLastUpdate>
	<SubCategoryStatus>Active</SubCategoryStatus>
    <SubCategoryAction></SubCategoryAction>
  </Order>
  <Order OrderID="10250">
    <CategoryID>2</CategoryID>
    <SubCategoryName>Sub Category 2</SubCategoryName>
    <SubCategoryTotal>Categories: 2 / Products: 09</SubCategoryTotal>
    <SubCategoryOperation></SubCategoryOperation>
    <SubCategoryLastUpdate>Feb 08 2016- 09:02</SubCategoryLastUpdate>
	<SubCategoryStatus>Inactive</SubCategoryStatus>
    <SubCategoryAction></SubCategoryAction>
  </Order>
</Orders>

